etc/init.d/tourbox
tourboxneo/__init__.py
tourboxneo/constants.py
tourboxneo/device.py
tourboxneo-0.2.dist-info/LICENSE.md
tourboxneo-0.2.dist-info/METADATA
tourboxneo-0.2.dist-info/WHEEL
tourboxneo-0.2.dist-info/entry_points.txt
tourboxneo-0.2.dist-info/top_level.txt
tourboxneo-0.2.dist-info/RECORD
