Metadata-Version: 2.1
Name: tourboxneo
Version: 0.2
Summary: Wrapper for TourBox (NEO) from Serial to uinput
Home-page: UNKNOWN
License: MIT License
Keywords: input,keyboard,usb,gadget
Platform: UNKNOWN
Classifier: License :: OSI Approved :: MIT License
Classifier: Operating System :: POSIX
Classifier: Topic :: System :: Hardware :: Universal Serial Bus (USB) :: Miscellaneous
Classifier: Topic :: System :: Hardware
License-File: LICENSE.md
Requires-Dist: pyserial
Requires-Dist: evdev
